cellink/__init__ .py
cellink/metrics.py
cellink/model.py
cellink/utils.py
cellink_luo-0.1.2.dist-info/LICENSE
cellink_luo-0.1.2.dist-info/METADATA
cellink_luo-0.1.2.dist-info/WHEEL
cellink_luo-0.1.2.dist-info/top_level.txt
cellink_luo-0.1.2.dist-info/RECORD
