Metadata-Version: 2.1
Name: cellink-luo
Version: 0.1.2
Summary: CelLink is an effecient python package for single-cell multi-omics integration, especially for datasets with weak feature linkage and imbalanced cell populations.
Author-email: Xin Luo <luosanj@umich.edu>
Project-URL: Homepage, https://github.com/liu-bioinfo-lab/CelLink
Project-URL: Issues, https://github.com/liu-bioinfo-lab/CelLink/issues
Classifier: Programming Language :: Python :: 3
Classifier: License :: OSI Approved :: MIT License
Classifier: Operating System :: OS Independent
Requires-Python: >=3.9
License-File: LICENSE
Requires-Dist: numpy==1.26.4
Requires-Dist: pandas==2.2.2
Requires-Dist: matplotlib==3.8.2
Requires-Dist: anndata==0.10.5.post1
Requires-Dist: scanpy==1.9.8
Requires-Dist: seaborn==0.13.2
Requires-Dist: POT==0.9.4
Requires-Dist: scipy==1.11.4
Requires-Dist: scikit-learn==1.4.0
Requires-Dist: networkx==3.2.1
